LICENSE
README.md
fairodds_auc/__init__.py
fairodds_auc/fairness.py
fairodds_auc/metrics.py
fairodds_auc-0.2.0.dist-info/METADATA
fairodds_auc-0.2.0.dist-info/WHEEL
fairodds_auc-0.2.0.dist-info/licenses/LICENSE
fairodds_auc-0.2.0.dist-info/RECORD
