Metadata-Version: 2.4
Name: fairodds-auc
Version: 0.2.0
Summary: FairOdds-AUC: A fairness-scaled AUROC metric that penalizes equalized odds gaps across sensitive attributes
Project-URL: Homepage, https://github.com/your-name/fairodds-auc
Project-URL: Repository, https://github.com/your-name/fairodds-auc
Project-URL: Issues, https://github.com/your-name/fairodds-auc/issues
Author: FairOdds-AUC Authors
License: MIT License
License-File: LICENSE
Keywords: auc,auroc,bias,equalized odds,fairness,metrics
Classifier: Development Status :: 4 - Beta
Classifier: Intended Audience :: Science/Research
Classifier: License :: OSI Approved :: MIT License
Classifier: Programming Language :: Python
Classifier: Programming Language :: Python :: 3
Classifier: Programming Language :: Python :: 3 :: Only
Classifier: Programming Language :: Python :: 3.8
Classifier: Programming Language :: Python :: 3.9
Classifier: Programming Language :: Python :: 3.10
Classifier: Programming Language :: Python :: 3.11
Classifier: Programming Language :: Python :: 3.12
Classifier: Topic :: Scientific/Engineering
Requires-Python: >=3.8
Requires-Dist: fairlearn>=0.10.0
Requires-Dist: numpy>=1.21
Requires-Dist: scikit-learn>=1.0
